{
  "_class": "document",
  "do_objectID": "383511AC-4C14-4FBC-8AE5-34943B4D558A",
  "assets": {
    "_class": "assetCollection",
    "colorAssets": [],
    "gradientAssets": [],
    "imageCollection": { "_class": "imageCollection", "images": {} },
    "images": [],
    "colors": [],
    "gradients": []
  },
  "colorSpace": 0,
  "currentPageIndex": 0,
  "foreignLayerStyles": [],
  "foreignSymbols": [],
  "foreignTextStyles": [],
  "layerStyles": { "_class": "sharedStyleContainer", "objects": [] },
  "layerSymbols": { "_class": "symbolContainer", "objects": [] },
  "layerTextStyles": { "_class": "sharedTextStyleContainer", "objects": [] },
  "pages": [
    {
      "_class": "MSJSONFileReference",
      "_ref_class": "MSImmutablePage",
      "_ref": "pages/57823E51-CA2F-4D65-8C5A-EB80DFBEDB1A"
    }
  ]
}
