{
  "_class": "document",
  "do_objectID": "A035FAC2-0948-4AA7-8E6F-84A24FFAB856",
  "colorSpace": 0,
  "currentPageIndex": 0,
  "assets": {
    "_class": "assetCollection",
    "do_objectID": "B526B67F-A41E-453F-BB27-C53EDD67A9B3",
    "images": [],
    "colorAssets": [],
    "exportPresets": [],
    "gradientAssets": [],
    "imageCollection": { "_class": "imageCollection", "images": {} },
    "colors": [],
    "gradients": []
  },
  "foreignLayerStyles": [],
  "foreignSymbols": [],
  "foreignTextStyles": [],
  "layerStyles": { "_class": "sharedStyleContainer", "objects": [] },
  "layerSymbols": { "_class": "symbolContainer", "objects": [] },
  "layerTextStyles": { "_class": "sharedTextStyleContainer", "objects": [] },
  "pages": [
    {
      "_class": "MSJSONFileReference",
      "_ref_class": "MSImmutablePage",
      "_ref": "pages/15505001-8626-441B-A50C-710D6808A778"
    }
  ]
}
