{
  "_class": "document",
  "do_objectID": "C10FDCE5-FB51-4DD3-8CD7-A5B90D258A1C",
  "assets": {
    "_class": "assetCollection",
    "colorAssets": [],
    "gradientAssets": [],
    "imageCollection": { "_class": "imageCollection", "images": {} },
    "images": [],
    "colors": [],
    "gradients": []
  },
  "colorSpace": 0,
  "currentPageIndex": 0,
  "foreignLayerStyles": [],
  "foreignSymbols": [],
  "foreignTextStyles": [],
  "layerStyles": { "_class": "sharedStyleContainer", "objects": [] },
  "layerSymbols": { "_class": "symbolContainer", "objects": [] },
  "layerTextStyles": { "_class": "sharedTextStyleContainer", "objects": [] },
  "pages": [
    {
      "_class": "MSJSONFileReference",
      "_ref_class": "MSImmutablePage",
      "_ref": "pages/D8585C3A-7597-4AED-A917-D50C192C4235"
    }
  ]
}
