{
  "_class": "document",
  "do_objectID": "36C0EEB1-A754-45B4-B294-089F29EAD40A",
  "assets": {
    "_class": "assetCollection",
    "colorAssets": [],
    "gradientAssets": [],
    "imageCollection": { "_class": "imageCollection", "images": {} },
    "images": [],
    "colors": [],
    "gradients": []
  },
  "colorSpace": 0,
  "currentPageIndex": 0,
  "foreignLayerStyles": [],
  "foreignSymbols": [],
  "foreignTextStyles": [],
  "layerStyles": { "_class": "sharedStyleContainer", "objects": [] },
  "layerSymbols": { "_class": "symbolContainer", "objects": [] },
  "layerTextStyles": { "_class": "sharedTextStyleContainer", "objects": [] },
  "pages": [
    {
      "_class": "MSJSONFileReference",
      "_ref_class": "MSImmutablePage",
      "_ref": "pages/96954714-F51A-4F1D-9DC2-1971903DCF0B"
    }
  ]
}
