{
  "_class": "document",
  "do_objectID": "B6269202-EC9F-4BF4-8EF3-1FF0F774543A",
  "colorSpace": 0,
  "currentPageIndex": 0,
  "assets": {
    "_class": "assetCollection",
    "do_objectID": "F67BA1C7-ADCE-4E67-93BE-64FCE1FA8B3C",
    "images": [],
    "colorAssets": [],
    "exportPresets": [],
    "gradientAssets": [],
    "imageCollection": { "_class": "imageCollection", "images": {} },
    "colors": [],
    "gradients": []
  },
  "foreignLayerStyles": [],
  "foreignSymbols": [],
  "foreignTextStyles": [],
  "layerStyles": { "_class": "sharedStyleContainer", "objects": [] },
  "layerSymbols": { "_class": "symbolContainer", "objects": [] },
  "layerTextStyles": { "_class": "sharedTextStyleContainer", "objects": [] },
  "pages": [
    {
      "_class": "MSJSONFileReference",
      "_ref_class": "MSImmutablePage",
      "_ref": "pages/73265D2B-6B9C-4498-9D2E-2CE31E3B93C5"
    }
  ]
}
